shared_memory/__init__.py
shared_memory/_version.py
shared_memory/_winshmem.cp36-win_amd64.pyd
shared_memory/managers.py
shared_memory/resource_tracker.py
shared_memory/shared_memory.py
shared_memory38-0.1.3.dist-info/LICENSE
shared_memory38-0.1.3.dist-info/METADATA
shared_memory38-0.1.3.dist-info/WHEEL
shared_memory38-0.1.3.dist-info/top_level.txt
shared_memory38-0.1.3.dist-info/RECORD
