Metadata-Version: 2.1
Name: shared-memory38
Version: 0.1.3
Summary: Backport of multiprocessing.shared_memory in Python 3.8
Home-page: https://github.com/mars-project/shared_memory38
Author: Wenjun Si
Author-email: swj0066@gmail.com
License: PSF license
Platform: UNKNOWN
Classifier: License :: OSI Approved :: Python Software Foundation License
Classifier: Operating System :: OS Independent
Classifier: Programming Language :: Python
Classifier: Programming Language :: Python :: 3.6
Classifier: Programming Language :: Python :: 3.7
Classifier: Programming Language :: Python :: Implementation :: CPython
Classifier: Topic :: Software Development :: Libraries
License-File: LICENSE
